wonder/__init__.py
wonder/pulldata.py
wonderpy/__init__.py
wonderpy/pulldata.py
cdcwonderpy-0.0.1.dist-info/METADATA
cdcwonderpy-0.0.1.dist-info/WHEEL
cdcwonderpy-0.0.1.dist-info/top_level.txt
cdcwonderpy-0.0.1.dist-info/RECORD
