Metadata-Version: 2.1
Name: cdcwonderpy
Version: 0.0.1
Summary: A Python package to automatically fill out the CDC WONDER MCD form
Home-page: https://github.com/tlcaputi/cdcwonderpy
Author: Theodore L Caputi
Author-email: tcaputi@gmail.com
License: No License
Platform: UNKNOWN
